oremda/server/__init__.py
oremda/server/api/api_v1/api.py
oremda/server/api/api_v1/endpoints/operators.py
oremda/server/api/api_v1/endpoints/pipelines.py
oremda/server/api/api_v1/endpoints/rpc.py
oremda/server/api/api_v1/endpoints/sessions.py
oremda/server/api/api_v1/endpoints/websockets.py
oremda/server/cli.py
oremda/server/context.py
oremda/server/index.html
oremda/server/main.py
oremda/server/pipeline_1d.json
oremda/server/pipeline_2d.json
oremda/server/utils.py
oremda_server-0.0.3.dist-info/entry_points.txt
oremda_server-0.0.3.dist-info/WHEEL
oremda_server-0.0.3.dist-info/METADATA
oremda_server-0.0.3.dist-info/RECORD
