Metadata-Version: 2.1
Name: oremda-server
Version: 0.0.3
Summary: 
License: BSD-3-Clause
Author: Alessandro Genova
Author-email: alessandro.genova@kitware.com
Requires-Python: >=3.8,<4.0
Classifier: License :: OSI Approved :: BSD License
Classifier: Programming Language :: Python :: 3
Classifier: Programming Language :: Python :: 3.10
Classifier: Programming Language :: Python :: 3.8
Classifier: Programming Language :: Python :: 3.9
Requires-Dist: fastapi (>=0.73.0,<0.74.0)
Requires-Dist: fastapi-websocket-rpc (>=0.1.21,<0.2.0)
Requires-Dist: msgpack (>=1.0.3,<2.0.0)
Requires-Dist: oremda-cli (>=0.0.2,<0.0.3)
Requires-Dist: oremda-core (>=0.0.2,<0.0.3)
Requires-Dist: oremda-engine (>=0.0.4,<0.0.5)
Requires-Dist: uvicorn[standard] (>=0.17.0,<0.18.0)
